README.md
setup.py
djblockchain/__init__.py
djblockchain/admin.py
djblockchain/crudlfap.py
djblockchain/demo.py
djblockchain/ethereum.py
djblockchain/fake.py
djblockchain/models.py
djblockchain/provider.py
djblockchain/serializers.py
djblockchain/test_models.py
djblockchain/test_settings.py
djblockchain/tezos.py
djblockchain/views.py
djblockchain.egg-info/PKG-INFO
djblockchain.egg-info/SOURCES.txt
djblockchain.egg-info/dependency_links.txt
djblockchain.egg-info/requires.txt
djblockchain.egg-info/top_level.txt
djblockchain/migrations/0001_initial.py
djblockchain/migrations/0002_transaction_contract.py
djblockchain/migrations/0003_auto_20191110_1930.py
djblockchain/migrations/0004_auto_20191111_1740.py
djblockchain/migrations/0005_blockchain_explorer.py
djblockchain/migrations/0006_unique_blockchain_address.py
djblockchain/migrations/0007_blockchain_confirmation_blocks.py
djblockchain/migrations/0008_blockchain_is_active.py
djblockchain/migrations/0009_auto_20200109_1647.py
djblockchain/migrations/0010_auto_20200123_0928.py
djblockchain/migrations/0011_remove_address_unicity_constraint.py
djblockchain/migrations/0012_txhash_unique.py
djblockchain/migrations/0013_auto_20200512_2321.py
djblockchain/migrations/0014_transaction_history.py
djblockchain/migrations/0015_remove_deprecated_hold_status_accepted.py
djblockchain/migrations/0016_index_transaction_state.py
djblockchain/migrations/0017_jsonfield.py
djblockchain/migrations/__init__.py