Metadata-Version: 2.1
Name: djblockchain
Version: 0.1.0
Summary: djblockchain is a Django app which provides tables to store data about
Home-page: https://yourlabs.io/oss/cli2
Author: James Pic
Author-email: jamespic@gmail.com
License: MIT
Keywords: cli
Platform: UNKNOWN
Requires-Python: >=3.8
Provides-Extra: test
